imagescrapper/__init__.py
imagescrapper/logger.py
imagescrapper/runner.py
image_scrapper_pk1308-1.0.0.dist-info/LICENSE
image_scrapper_pk1308-1.0.0.dist-info/METADATA
image_scrapper_pk1308-1.0.0.dist-info/WHEEL
image_scrapper_pk1308-1.0.0.dist-info/top_level.txt
image_scrapper_pk1308-1.0.0.dist-info/RECORD
